.DS_Store
facedetector/FaceDetector.py
facedetector/__init__.py
facedetector/utils.py
facedetector/util/__init__.py
facedetector/util/align.py
facedetector/util/detector.py
facedetector/util/geometry.py
src/FaceDetector.py
src/__init__.py
src/utils.py
src/util/__init__.py
src/util/align.py
src/util/detector.py
src/util/geometry.py
tests/FaceDetector_test.py
tests/__init__.py
facedetector_py-0.0.4.dist-info/LICENSE
facedetector_py-0.0.4.dist-info/METADATA
facedetector_py-0.0.4.dist-info/WHEEL
facedetector_py-0.0.4.dist-info/top_level.txt
facedetector_py-0.0.4.dist-info/RECORD
