Metadata-Version: 2.1
Name: facedetector-py
Version: 0.0.4
Summary: Python script for detecting faces in an image
Home-page: https://github.com/freearhey/facedetector
Author: Arhey
License: MIT
Requires-Python: >=3.5.5
License-File: LICENSE
Requires-Dist: retina-face (>=0.0.12)
Requires-Dist: numpy (>=1.14.0)
Provides-Extra: dev
Requires-Dist: pytest (>=7.0) ; extra == 'dev'
Requires-Dist: twine (>=4.0.2) ; extra == 'dev'
